intellidocs/__init__.py
intellidocs/contracts.py
intellidocs/document_creators.py
intellidocs/py.typed
intellidocs/types.py
intellidocs-0.0.1.dist-info/METADATA
intellidocs-0.0.1.dist-info/WHEEL
intellidocs-0.0.1.dist-info/entry_points.txt
intellidocs-0.0.1.dist-info/RECORD
